yta_voice_module/__init__.py
yta_voice_module/experimental/__init__.py
yta_voice_module/stt/__init__.py
yta_voice_module/stt/whisper.py
yta_voice_module/test/__init__.py
yta_voice_module/test/resources/__init__.py
yta_voice_module/tts/__init__.py
yta_voice_module/tts/coqui.py
yta_voice_module/tts/google.py
yta_voice_module/tts/microsoft.py
yta_voice_module/tts/open_voice.py
yta_voice_module/tts/tortoise.py
yta_voice_module-0.0.6.dist-info/LICENSE
yta_voice_module-0.0.6.dist-info/METADATA
yta_voice_module-0.0.6.dist-info/WHEEL
yta_voice_module-0.0.6.dist-info/top_level.txt
yta_voice_module-0.0.6.dist-info/RECORD
