Metadata-Version: 2.1
Name: yta-voice-module
Version: 0.0.6
Summary: Youtube Autónomo Voice module is here.
Home-page: UNKNOWN
Author: Daniel Alcalá
Author-email: <danielalcalavalera@gmail.com>
License: UNKNOWN
Keywords: youtube autonomo voice utils module
Platform: UNKNOWN
Classifier: Development Status :: 3 - Alpha
Classifier: Intended Audience :: Education
Classifier: Programming Language :: Python :: 2
Classifier: Programming Language :: Python :: 3
Classifier: Operating System :: MacOS :: MacOS X
Classifier: Operating System :: Microsoft :: Windows
Requires-Dist: pyttsx3
Requires-Dist: gTTS
